{
  "ID": "4f6a59d2-d1b2-4c8e-97e6-97ea830d333a",
  "Version": "2.3.4",
  "Name": "ShopTabItem",
  "Content": {
    "Content": {
      "Animation": {
        "Duration": 0,
        "Speed": 1.0,
        "Timelines": [],
        "ctype": "TimelineActionData"
      },
      "AnimationList": [],
      "ObjectData": {
        "Tag": 53,
        "Children": [
          {
            "ClipAble": false,
            "BackColorAlpha": 0,
            "ComboBoxIndex": 1,
            "SingleColor": {
              "R": 150,
              "G": 200
            },
            "FirstColor": {
              "R": 150,
              "G": 200
            },
            "EndColor": {},
            "ColorVector": {
              "ScaleY": 1.0
            },
            "Scale9Width": 1,
            "Scale9Height": 1,
            "StretchWidthEnable": true,
            "AnchorPoint": {},
            "Position": {
              "X": 5.68,
              "Y": 1.152
            },
            "Scale": {
              "ScaleX": 1.0,
              "ScaleY": 1.0
            },
            "CColor": {},
            "IconVisible": false,
            "PositionPercentXEnabled": true,
            "PrePosition": {
              "X": 0.005,
              "Y": 0.0018
            },
            "PreSize": {
              "X": 0.8891,
              "Y": 0.8281
            },
            "LeftMargin": 5.68,
            "RightMargin": 120.3024,
            "TopMargin": 108.848,
            "BottomMargin": 1.152,
            "Tag": 72,
            "Children": [
              {
                "ClipAble": false,
                "BackColorAlpha": 0,
                "ComboBoxIndex": 1,
                "SingleColor": {
                  "R": 150,
                  "G": 200
                },
                "FirstColor": {
                  "R": 150,
                  "G": 200
                },
                "EndColor": {},
                "ColorVector": {
                  "ScaleY": 1.0
                },
                "Scale9Width": 1,
                "Scale9Height": 1,
                "StretchWidthEnable": true,
                "AnchorPoint": {},
                "Position": {
                  "X": 5.0,
                  "Y": 14.787
                },
                "Scale": {
                  "ScaleX": 1.0,
                  "ScaleY": 1.0
                },
                "CColor": {},
                "IconVisible": false,
                "PrePosition": {
                  "X": 0.005,
                  "Y": 0.0279
                },
                "PreSize": {
                  "X": 0.9901,
                  "Y": 0.8396
                },
                "HorizontalEdge": "BothEdge",
                "VerticalEdge": "BothEdge",
                "LeftMargin": 5.0,
                "RightMargin": 5.0176,
                "TopMargin": 70.213,
                "BottomMargin": 14.787,
                "Tag": 87,
                "ActionTag": 93556273,
                "Size": {
                  "X": 1000.0,
                  "Y": 445.0
                },
                "Name": "pnContent",
                "ctype": "PanelObjectData"
              },
              {
                "ClipAble": false,
                "BackColorAlpha": 0,
                "ComboBoxIndex": 1,
                "SingleColor": {
                  "R": 150,
                  "G": 200
                },
                "FirstColor": {
                  "R": 150,
                  "G": 200
                },
                "EndColor": {},
                "ColorVector": {
                  "ScaleY": 1.0
                },
                "Scale9Width": 1,
                "Scale9Height": 1,
                "StretchWidthEnable": true,
                "AnchorPoint": {
                  "ScaleY": 1.0
                },
                "Position": {
                  "X": 5.0,
                  "Y": 495.0
                },
                "Scale": {
                  "ScaleX": 1.0,
                  "ScaleY": 1.0
                },
                "CColor": {},
                "IconVisible": false,
                "PrePosition": {
                  "X": 0.005,
                  "Y": 0.934
                },
                "PreSize": {
                  "X": 1.0,
                  "Y": 0.1132
                },
                "HorizontalEdge": "BothEdge",
                "VerticalEdge": "TopEdge",
                "LeftMargin": 5.0,
                "RightMargin": -4.9824,
                "TopMargin": 35.0,
                "BottomMargin": 435.0,
                "Tag": 186,
                "Children": [
                  {
                    "FileData": {
                      "Type": "PlistSubImage",
                      "Path": "achievement_Lines.png",
                      "Plist": "Achievement/res/Achievement_new.plist"
                    },
                    "Scale9OriginX": 101,
                    "Scale9Width": 107,
                    "Scale9Height": 2,
                    "StretchWidthEnable": true,
                    "AnchorPoint": {
                      "ScaleX": 0.5,
                      "ScaleY": 0.5
                    },
                    "Position": {
                      "X": 505.0,
                      "Y": 66.0
                    },
                    "Scale": {
                      "ScaleX": 1.0,
                      "ScaleY": 1.0
                    },
                    "CColor": {},
                    "IconVisible": false,
                    "PositionPercentXEnabled": true,
                    "PositionPercentYEnabled": true,
                    "PrePosition": {
                      "X": 0.5,
                      "Y": 1.1
                    },
                    "PreSize": {
                      "X": 1.0,
                      "Y": 0.1667
                    },
                    "TopMargin": -11.0,
                    "BottomMargin": 61.0,
                    "Tag": 187,
                    "ActionTag": -1437697785,
                    "Size": {
                      "X": 1010.0,
                      "Y": 10.0
                    },
                    "Name": "imgLine",
                    "ctype": "ImageViewObjectData"
                  },
                  {
                    "FontSize": 36,
                    "LabelText": "Cue Boxes",
                    "FontResource": {
                      "Type": "Normal",
                      "Path": "Font/facebook.TTF",
                      "Plist": ""
                    },
                    "HorizontalAlignmentType": "HT_Center",
                    "OutlineColor": {
                      "G": 0,
                      "B": 0
                    },
                    "ShadowColor": {
                      "R": 110,
                      "G": 110,
                      "B": 110
                    },
                    "ShadowOffsetX": 2.0,
                    "ShadowOffsetY": -2.0,
                    "ShadowEnabled": true,
                    "AnchorPoint": {
                      "ScaleX": 0.5,
                      "ScaleY": 0.5
                    },
                    "Position": {
                      "X": 513.989,
                      "Y": 39.0
                    },
                    "Scale": {
                      "ScaleX": 1.0,
                      "ScaleY": 1.0
                    },
                    "RotationSkewX": 7.0,
                    "CColor": {
                      "R": 30,
                      "G": 235
                    },
                    "IconVisible": false,
                    "PositionPercentXEnabled": true,
                    "PositionPercentYEnabled": true,
                    "PrePosition": {
                      "X": 0.5089,
                      "Y": 0.65
                    },
                    "PreSize": {
                      "X": 0.1743,
                      "Y": 0.8667
                    },
                    "LeftMargin": 425.989,
                    "RightMargin": 408.011,
                    "TopMargin": -5.0,
                    "BottomMargin": 13.0,
                    "Tag": 81,
                    "ActionTag": -1609333605,
                    "Size": {
                      "X": 176.0,
                      "Y": 52.0
                    },
                    "Name": "title",
                    "ctype": "TextObjectData"
                  },
                  {
                    "FileData": {
                      "Type": "Normal",
                      "Path": "Shop/res/BLACKMARKET/Blue_Lines.png",
                      "Plist": ""
                    },
                    "BlendFunc": {
                      "Src": 1,
                      "Dst": 771
                    },
                    "AnchorPoint": {
                      "ScaleX": 0.5,
                      "ScaleY": 0.5
                    },
                    "Position": {
                      "X": 367.943,
                      "Y": 31.0
                    },
                    "Scale": {
                      "ScaleX": 1.0,
                      "ScaleY": 1.0
                    },
                    "RotationSkewY": 180.0,
                    "CColor": {},
                    "IconVisible": false,
                    "PositionPercentXEnabled": true,
                    "PrePosition": {
                      "X": 0.3643,
                      "Y": 0.5167
                    },
                    "PreSize": {
                      "X": 0.1158,
                      "Y": 0.1667
                    },
                    "LeftMargin": 309.443,
                    "RightMargin": 583.557,
                    "TopMargin": 24.0,
                    "BottomMargin": 26.0,
                    "Tag": 103,
                    "ActionTag": 1328842211,
                    "Size": {
                      "X": 117.0,
                      "Y": 10.0
                    },
                    "Name": "Blue_Lines_2",
                    "ctype": "SpriteObjectData"
                  },
                  {
                    "FileData": {
                      "Type": "Normal",
                      "Path": "Shop/res/BLACKMARKET/Blue_Lines.png",
                      "Plist": ""
                    },
                    "BlendFunc": {
                      "Src": 1,
                      "Dst": 771
                    },
                    "AnchorPoint": {
                      "ScaleX": 0.5,
                      "ScaleY": 0.5
                    },
                    "Position": {
                      "X": 662.358,
                      "Y": 31.0
                    },
                    "Scale": {
                      "ScaleX": 1.0,
                      "ScaleY": 1.0
                    },
                    "CColor": {},
                    "IconVisible": false,
                    "PositionPercentXEnabled": true,
                    "PrePosition": {
                      "X": 0.6558,
                      "Y": 0.5167
                    },
                    "PreSize": {
                      "X": 0.1158,
                      "Y": 0.1667
                    },
                    "LeftMargin": 603.858,
                    "RightMargin": 289.142,
                    "TopMargin": 24.0,
                    "BottomMargin": 26.0,
                    "Tag": 102,
                    "ActionTag": -1250156873,
                    "Size": {
                      "X": 117.0,
                      "Y": 10.0
                    },
                    "Name": "Blue_Lines_1",
                    "ctype": "SpriteObjectData"
                  },
                  {
                    "FileData": {
                      "Type": "PlistSubImage",
                      "Path": "achievement_Lines.png",
                      "Plist": "Achievement/res/Achievement_new.plist"
                    },
                    "Scale9OriginX": 101,
                    "Scale9Width": 107,
                    "Scale9Height": 2,
                    "StretchWidthEnable": true,
                    "AnchorPoint": {
                      "ScaleX": 0.5,
                      "ScaleY": 0.5
                    },
                    "Position": {
                      "X": 0.4789,
                      "Y": 118.8515
                    },
                    "Scale": {
                      "ScaleX": 1.0,
                      "ScaleY": 1.0
                    },
                    "CColor": {},
                    "IconVisible": false,
                    "PrePosition": {
                      "X": 0.0005,
                      "Y": 1.9809
                    },
                    "PreSize": {
                      "X": 0.0,
                      "Y": 0.1667
                    },
                    "VerticalEdge": "TopEdge",
                    "LeftMargin": 0.4789,
                    "RightMargin": 1009.5211,
                    "TopMargin": -63.8515,
                    "BottomMargin": 113.8515,
                    "Tag": 82,
                    "ActionTag": 982905159,
                    "Size": {
                      "X": 0.0,
                      "Y": 10.0
                    },
                    "Name": "imgLine",
                    "ctype": "ImageViewObjectData"
                  },
                  {
                    "ClipAble": false,
                    "BackColorAlpha": 0,
                    "FileData": {
                      "Type": "Normal",
                      "Path": "Shop/res/BLACKMARKET/Search_Pricedescending_box_02.png",
                      "Plist": ""
                    },
                    "ComboBoxIndex": 1,
                    "SingleColor": {
                      "R": 150,
                      "G": 200
                    },
                    "FirstColor": {
                      "R": 150,
                      "G": 200
                    },
                    "EndColor": {},
                    "ColorVector": {
                      "ScaleY": 1.0
                    },
                    "Scale9Enable": true,
                    "Scale9OriginX": 79,
                    "Scale9OriginY": 70,
                    "Scale9Width": 84,
                    "Scale9Height": 75,
                    "TouchEnable": true,
                    "StretchWidthEnable": true,
                    "StretchHeightEnable": true,
                    "AnchorPoint": {
                      "ScaleX": 0.5,
                      "ScaleY": 0.5
                    },
                    "Position": {
                      "X": 860.52,
                      "Y": -53.796
                    },
                    "Scale": {
                      "ScaleX": 1.0,
                      "ScaleY": 1.0
                    },
                    "CColor": {},
                    "IconVisible": false,
                    "PrePosition": {
                      "X": 0.852,
                      "Y": -0.8966
                    },
                    "PreSize": {
                      "X": 0.2574,
                      "Y": 3.5
                    },
                    "HorizontalEdge": "RightEdge",
                    "VerticalEdge": "TopEdge",
                    "LeftMargin": 730.52,
                    "RightMargin": 19.48,
                    "TopMargin": 8.796,
                    "BottomMargin": -158.796,
                    "Tag": 55,
                    "Children": [
                      {
                        "FontSize": 14,
                        "ButtonText": "",
                        "TextColor": {
                          "R": 65,
                          "G": 65,
                          "B": 70
                        },
                        "DisabledFileData": {
                          "Type": "Default",
                          "Path": "Default/Button_Disable.png",
                          "Plist": ""
                        },
                        "Scale9Enable": true,
                        "Scale9OriginX": -15,
                        "Scale9OriginY": -11,
                        "Scale9Width": 30,
                        "Scale9Height": 22,
                        "OutlineColor": {
                          "G": 0,
                          "B": 0
                        },
                        "ShadowColor": {
                          "R": 110,
                          "G": 110,
                          "B": 110
                        },
                        "ShadowOffsetX": 2.0,
                        "ShadowOffsetY": -2.0,
                        "TouchEnable": true,
                        "AnchorPoint": {
                          "ScaleX": 0.5,
                          "ScaleY": 0.5
                        },
                        "Position": {
                          "X": 130.0,
                          "Y": 157.5
                        },
                        "Scale": {
                          "ScaleX": 1.0,
                          "ScaleY": 1.0
                        },
                        "CColor": {},
                        "IconVisible": false,
                        "PositionPercentXEnabled": true,
                        "PositionPercentYEnabled": true,
                        "PrePosition": {
                          "X": 0.5,
                          "Y": 0.75
                        },
                        "PreSize": {
                          "X": 0.8846,
                          "Y": 0.1667
                        },
                        "LeftMargin": 15.0,
                        "RightMargin": 15.0,
                        "TopMargin": 35.0,
                        "BottomMargin": 140.0,
                        "Tag": 22,
                        "Children": [
                          {
                            "FontSize": 26,
                            "LabelText": "Price Descending",
                            "FontResource": {
                              "Type": "Normal",
                              "Path": "Font/facebook.TTF",
                              "Plist": ""
                            },
                            "OutlineColor": {
                              "G": 0,
                              "B": 0
                            },
                            "ShadowColor": {
                              "R": 110,
                              "G": 110,
                              "B": 110
                            },
                            "ShadowOffsetX": 2.0,
                            "ShadowOffsetY": -2.0,
                            "AnchorPoint": {
                              "ScaleX": 0.5,
                              "ScaleY": 0.5
                            },
                            "Position": {
                              "X": 115.0,
                              "Y": 17.5
                            },
                            "Scale": {
                              "ScaleX": 1.0,
                              "ScaleY": 1.0
                            },
                            "RotationSkewX": 7.0002,
                            "CColor": {},
                            "IconVisible": false,
                            "PositionPercentXEnabled": true,
                            "PositionPercentYEnabled": true,
                            "PrePosition": {
                              "X": 0.5,
                              "Y": 0.5
                            },
                            "PreSize": {
                              "X": 0.8913,
                              "Y": 1.0857
                            },
                            "LeftMargin": 12.5,
                            "RightMargin": 12.5,
                            "TopMargin": -1.5,
                            "BottomMargin": -1.5,
                            "Tag": 23,
                            "ActionTag": -517394791,
                            "Size": {
                              "X": 205.0,
                              "Y": 38.0
                            },
                            "Name": "lbText",
                            "ctype": "TextObjectData"
                          }
                        ],
                        "ActionTag": 1721061099,
                        "Size": {
                          "X": 230.0,
                          "Y": 35.0
                        },
                        "Name": "btn_price_descending",
                        "ctype": "ButtonObjectData"
                      },
                      {
                        "FontSize": 14,
                        "ButtonText": "",
                        "TextColor": {
                          "R": 65,
                          "G": 65,
                          "B": 70
                        },
                        "DisabledFileData": {
                          "Type": "Default",
                          "Path": "Default/Button_Disable.png",
                          "Plist": ""
                        },
                        "Scale9Enable": true,
                        "Scale9OriginX": -15,
                        "Scale9OriginY": -11,
                        "Scale9Width": 30,
                        "Scale9Height": 22,
                        "OutlineColor": {
                          "G": 0,
                          "B": 0
                        },
                        "ShadowColor": {
                          "R": 110,
                          "G": 110,
                          "B": 110
                        },
                        "ShadowOffsetX": 2.0,
                        "ShadowOffsetY": -2.0,
                        "TouchEnable": true,
                        "AnchorPoint": {
                          "ScaleX": 0.5,
                          "ScaleY": 0.5
                        },
                        "Position": {
                          "X": 130.0,
                          "Y": 123.9
                        },
                        "Scale": {
                          "ScaleX": 1.0,
                          "ScaleY": 1.0
                        },
                        "CColor": {},
                        "IconVisible": false,
                        "PositionPercentXEnabled": true,
                        "PositionPercentYEnabled": true,
                        "PrePosition": {
                          "X": 0.5,
                          "Y": 0.59
                        },
                        "PreSize": {
                          "X": 0.8846,
                          "Y": 0.1667
                        },
                        "LeftMargin": 15.0,
                        "RightMargin": 15.0,
                        "TopMargin": 68.6,
                        "BottomMargin": 106.4,
                        "Tag": 13,
                        "Children": [
                          {
                            "FontSize": 26,
                            "LabelText": "Price Ascending",
                            "FontResource": {
                              "Type": "Normal",
                              "Path": "Font/facebook.TTF",
                              "Plist": ""
                            },
                            "OutlineColor": {
                              "G": 0,
                              "B": 0
                            },
                            "ShadowColor": {
                              "R": 110,
                              "G": 110,
                              "B": 110
                            },
                            "ShadowOffsetX": 2.0,
                            "ShadowOffsetY": -2.0,
                            "AnchorPoint": {
                              "ScaleX": 0.5,
                              "ScaleY": 0.5
                            },
                            "Position": {
                              "X": 115.0,
                              "Y": 17.5
                            },
                            "Scale": {
                              "ScaleX": 1.0,
                              "ScaleY": 1.0
                            },
                            "RotationSkewX": 7.0002,
                            "CColor": {},
                            "IconVisible": false,
                            "PositionPercentXEnabled": true,
                            "PositionPercentYEnabled": true,
                            "PrePosition": {
                              "X": 0.5,
                              "Y": 0.5
                            },
                            "PreSize": {
                              "X": 0.8391,
                              "Y": 1.0857
                            },
                            "LeftMargin": 18.5,
                            "RightMargin": 18.5,
                            "TopMargin": -1.5,
                            "BottomMargin": -1.5,
                            "Tag": 14,
                            "ActionTag": 630680324,
                            "Size": {
                              "X": 193.0,
                              "Y": 38.0
                            },
                            "Name": "lbText",
                            "ctype": "TextObjectData"
                          }
                        ],
                        "ActionTag": 168322109,
                        "Size": {
                          "X": 230.0,
                          "Y": 35.0
                        },
                        "Name": "btn_price_ascending",
                        "ctype": "ButtonObjectData"
                      },
                      {
                        "FontSize": 14,
                        "ButtonText": "",
                        "TextColor": {
                          "R": 65,
                          "G": 65,
                          "B": 70
                        },
                        "DisabledFileData": {
                          "Type": "Default",
                          "Path": "Default/Button_Disable.png",
                          "Plist": ""
                        },
                        "Scale9Enable": true,
                        "Scale9OriginX": -15,
                        "Scale9OriginY": -11,
                        "Scale9Width": 30,
                        "Scale9Height": 22,
                        "OutlineColor": {
                          "G": 0,
                          "B": 0
                        },
                        "ShadowColor": {
                          "R": 110,
                          "G": 110,
                          "B": 110
                        },
                        "ShadowOffsetX": 2.0,
                        "ShadowOffsetY": -2.0,
                        "TouchEnable": true,
                        "AnchorPoint": {
                          "ScaleX": 0.5,
                          "ScaleY": 0.5
                        },
                        "Position": {
                          "X": 130.0,
                          "Y": 90.3
                        },
                        "Scale": {
                          "ScaleX": 1.0,
                          "ScaleY": 1.0
                        },
                        "CColor": {},
                        "IconVisible": false,
                        "PositionPercentXEnabled": true,
                        "PositionPercentYEnabled": true,
                        "PrePosition": {
                          "X": 0.5,
                          "Y": 0.43
                        },
                        "PreSize": {
                          "X": 0.8846,
                          "Y": 0.1667
                        },
                        "LeftMargin": 15.0,
                        "RightMargin": 15.0,
                        "TopMargin": 102.2,
                        "BottomMargin": 72.8,
                        "Tag": 17,
                        "Children": [
                          {
                            "FontSize": 26,
                            "LabelText": "Prefer Break",
                            "FontResource": {
                              "Type": "Normal",
                              "Path": "Font/facebook.TTF",
                              "Plist": ""
                            },
                            "OutlineColor": {
                              "G": 0,
                              "B": 0
                            },
                            "ShadowColor": {
                              "R": 110,
                              "G": 110,
                              "B": 110
                            },
                            "ShadowOffsetX": 2.0,
                            "ShadowOffsetY": -2.0,
                            "AnchorPoint": {
                              "ScaleX": 0.5,
                              "ScaleY": 0.5
                            },
                            "Position": {
                              "X": 115.0,
                              "Y": 17.5
                            },
                            "Scale": {
                              "ScaleX": 1.0,
                              "ScaleY": 1.0
                            },
                            "RotationSkewX": 7.0,
                            "CColor": {},
                            "IconVisible": false,
                            "PositionPercentXEnabled": true,
                            "PositionPercentYEnabled": true,
                            "PrePosition": {
                              "X": 0.5,
                              "Y": 0.5
                            },
                            "PreSize": {
                              "X": 0.6826,
                              "Y": 1.0857
                            },
                            "LeftMargin": 36.5,
                            "RightMargin": 36.5,
                            "TopMargin": -1.5,
                            "BottomMargin": -1.5,
                            "Tag": 18,
                            "ActionTag": 1795520865,
                            "Size": {
                              "X": 157.0,
                              "Y": 38.0
                            },
                            "Name": "lbText",
                            "ctype": "TextObjectData"
                          }
                        ],
                        "ActionTag": 1390247549,
                        "Size": {
                          "X": 230.0,
                          "Y": 35.0
                        },
                        "Name": "btn_prefer_break",
                        "ctype": "ButtonObjectData"
                      },
                      {
                        "FontSize": 14,
                        "ButtonText": "",
                        "TextColor": {
                          "R": 65,
                          "G": 65,
                          "B": 70
                        },
                        "DisabledFileData": {
                          "Type": "Default",
                          "Path": "Default/Button_Disable.png",
                          "Plist": ""
                        },
                        "Scale9Enable": true,
                        "Scale9OriginX": -15,
                        "Scale9OriginY": -11,
                        "Scale9Width": 30,
                        "Scale9Height": 22,
                        "OutlineColor": {
                          "G": 0,
                          "B": 0
                        },
                        "ShadowColor": {
                          "R": 110,
                          "G": 110,
                          "B": 110
                        },
                        "ShadowOffsetX": 2.0,
                        "ShadowOffsetY": -2.0,
                        "TouchEnable": true,
                        "AnchorPoint": {
                          "ScaleX": 0.5,
                          "ScaleY": 0.5
                        },
                        "Position": {
                          "X": 130.0,
                          "Y": 56.7
                        },
                        "Scale": {
                          "ScaleX": 1.0,
                          "ScaleY": 1.0
                        },
                        "CColor": {},
                        "IconVisible": false,
                        "PositionPercentXEnabled": true,
                        "PositionPercentYEnabled": true,
                        "PrePosition": {
                          "X": 0.5,
                          "Y": 0.27
                        },
                        "PreSize": {
                          "X": 0.8846,
                          "Y": 0.1667
                        },
                        "LeftMargin": 15.0,
                        "RightMargin": 15.0,
                        "TopMargin": 135.8,
                        "BottomMargin": 39.2,
                        "Tag": 19,
                        "Children": [
                          {
                            "FontSize": 26,
                            "LabelText": "Prefer Jump",
                            "FontResource": {
                              "Type": "Normal",
                              "Path": "Font/facebook.TTF",
                              "Plist": ""
                            },
                            "OutlineColor": {
                              "G": 0,
                              "B": 0
                            },
                            "ShadowColor": {
                              "R": 110,
                              "G": 110,
                              "B": 110
                            },
                            "ShadowOffsetX": 2.0,
                            "ShadowOffsetY": -2.0,
                            "AnchorPoint": {
                              "ScaleX": 0.5,
                              "ScaleY": 0.5
                            },
                            "Position": {
                              "X": 115.0,
                              "Y": 17.5
                            },
                            "Scale": {
                              "ScaleX": 1.0,
                              "ScaleY": 1.0
                            },
                            "RotationSkewX": 7.0,
                            "CColor": {},
                            "IconVisible": false,
                            "PositionPercentXEnabled": true,
                            "PositionPercentYEnabled": true,
                            "PrePosition": {
                              "X": 0.5,
                              "Y": 0.5
                            },
                            "PreSize": {
                              "X": 0.6565,
                              "Y": 1.0857
                            },
                            "LeftMargin": 39.5,
                            "RightMargin": 39.5,
                            "TopMargin": -1.5,
                            "BottomMargin": -1.5,
                            "Tag": 20,
                            "ActionTag": -1967232571,
                            "Size": {
                              "X": 151.0,
                              "Y": 38.0
                            },
                            "Name": "lbText",
                            "ctype": "TextObjectData"
                          }
                        ],
                        "ActionTag": 1102871435,
                        "Size": {
                          "X": 230.0,
                          "Y": 35.0
                        },
                        "Name": "btn_prefer_jump",
                        "ctype": "ButtonObjectData"
                      },
                      {
                        "FontSize": 14,
                        "ButtonText": "",
                        "TextColor": {
                          "R": 65,
                          "G": 65,
                          "B": 70
                        },
                        "DisabledFileData": {
                          "Type": "Default",
                          "Path": "Default/Button_Disable.png",
                          "Plist": ""
                        },
                        "Scale9Enable": true,
                        "Scale9OriginX": -15,
                        "Scale9OriginY": -11,
                        "Scale9Width": 30,
                        "Scale9Height": 22,
                        "OutlineColor": {
                          "G": 0,
                          "B": 0
                        },
                        "ShadowColor": {
                          "R": 110,
                          "G": 110,
                          "B": 110
                        },
                        "ShadowOffsetX": 2.0,
                        "ShadowOffsetY": -2.0,
                        "TouchEnable": true,
                        "AnchorPoint": {
                          "ScaleX": 0.5,
                          "ScaleY": 0.5
                        },
                        "Position": {
                          "X": 130.0,
                          "Y": 23.1
                        },
                        "Scale": {
                          "ScaleX": 1.0,
                          "ScaleY": 1.0
                        },
                        "CColor": {},
                        "IconVisible": false,
                        "PositionPercentXEnabled": true,
                        "PositionPercentYEnabled": true,
                        "PrePosition": {
                          "X": 0.5,
                          "Y": 0.11
                        },
                        "PreSize": {
                          "X": 0.8846,
                          "Y": 0.1667
                        },
                        "LeftMargin": 15.0,
                        "RightMargin": 15.0,
                        "TopMargin": 169.4,
                        "BottomMargin": 5.6,
                        "Tag": 21,
                        "Children": [
                          {
                            "FontSize": 26,
                            "LabelText": "Prefer Masses",
                            "FontResource": {
                              "Type": "Normal",
                              "Path": "Font/facebook.TTF",
                              "Plist": ""
                            },
                            "OutlineColor": {
                              "G": 0,
                              "B": 0
                            },
                            "ShadowColor": {
                              "R": 110,
                              "G": 110,
                              "B": 110
                            },
                            "ShadowOffsetX": 2.0,
                            "ShadowOffsetY": -2.0,
                            "AnchorPoint": {
                              "ScaleX": 0.5,
                              "ScaleY": 0.5
                            },
                            "Position": {
                              "X": 115.0,
                              "Y": 17.5
                            },
                            "Scale": {
                              "ScaleX": 1.0,
                              "ScaleY": 1.0
                            },
                            "RotationSkewX": 7.0,
                            "CColor": {},
                            "IconVisible": false,
                            "PositionPercentXEnabled": true,
                            "PositionPercentYEnabled": true,
                            "PrePosition": {
                              "X": 0.5,
                              "Y": 0.5
                            },
                            "PreSize": {
                              "X": 0.7913,
                              "Y": 1.0857
                            },
                            "LeftMargin": 24.0,
                            "RightMargin": 24.0,
                            "TopMargin": -1.5,
                            "BottomMargin": -1.5,
                            "Tag": 22,
                            "ActionTag": -453572514,
                            "Size": {
                              "X": 182.0,
                              "Y": 38.0
                            },
                            "Name": "lbText",
                            "ctype": "TextObjectData"
                          }
                        ],
                        "ActionTag": -2146668552,
                        "Size": {
                          "X": 230.0,
                          "Y": 35.0
                        },
                        "Name": "btn_prefer_masses",
                        "ctype": "ButtonObjectData"
                      }
                    ],
                    "ActionTag": 1638371673,
                    "Size": {
                      "X": 260.0,
                      "Y": 210.0
                    },
                    "Name": "nd_selection",
                    "ctype": "PanelObjectData"
                  },
                  {
                    "FontSize": 14,
                    "ButtonText": "",
                    "TextColor": {
                      "R": 65,
                      "G": 65,
                      "B": 70
                    },
                    "DisabledFileData": {
                      "Type": "Default",
                      "Path": "Default/Button_Disable.png",
                      "Plist": ""
                    },
                    "NormalFileData": {
                      "Type": "Normal",
                      "Path": "Shop/res/BLACKMARKET/img_box_search.png",
                      "Plist": ""
                    },
                    "Scale9OriginX": 15,
                    "Scale9OriginY": 11,
                    "Scale9Width": 220,
                    "Scale9Height": 35,
                    "OutlineColor": {
                      "G": 0,
                      "B": 0
                    },
                    "ShadowColor": {
                      "R": 110,
                      "G": 110,
                      "B": 110
                    },
                    "ShadowOffsetX": 2.0,
                    "ShadowOffsetY": -2.0,
                    "TouchEnable": true,
                    "StretchWidthEnable": true,
                    "AnchorPoint": {
                      "ScaleX": 0.5,
                      "ScaleY": 0.5
                    },
                    "Position": {
                      "X": 858.5,
                      "Y": 36.828
                    },
                    "Scale": {
                      "ScaleX": 1.0,
                      "ScaleY": 1.0
                    },
                    "CColor": {},
                    "IconVisible": false,
                    "PositionPercentYEnabled": true,
                    "PrePosition": {
                      "X": 0.85,
                      "Y": 0.6138
                    },
                    "PreSize": {
                      "X": 0.2772,
                      "Y": 0.7167
                    },
                    "HorizontalEdge": "RightEdge",
                    "LeftMargin": 718.5,
                    "RightMargin": 11.5,
                    "TopMargin": 1.672,
                    "BottomMargin": 15.328,
                    "Tag": 11,
                    "Children": [
                      {
                        "IsCustomSize": true,
                        "FontSize": 28,
                        "LabelText": "Sort...",
                        "FontResource": {
                          "Type": "Normal",
                          "Path": "Font/facebook.TTF",
                          "Plist": ""
                        },
                        "HorizontalAlignmentType": "HT_Center",
                        "VerticalAlignmentType": "VT_Center",
                        "OutlineColor": {
                          "G": 0,
                          "B": 0
                        },
                        "ShadowColor": {
                          "R": 110,
                          "G": 110,
                          "B": 110
                        },
                        "ShadowOffsetX": 2.0,
                        "ShadowOffsetY": -2.0,
                        "AnchorPoint": {
                          "ScaleX": 0.5,
                          "ScaleY": 0.5
                        },
                        "Position": {
                          "X": 126.0,
                          "Y": 23.65
                        },
                        "Scale": {
                          "ScaleX": 1.0,
                          "ScaleY": 1.0
                        },
                        "RotationSkewX": 5.0,
                        "CColor": {
                          "R": 144,
                          "G": 238,
                          "B": 144
                        },
                        "IconVisible": false,
                        "PositionPercentXEnabled": true,
                        "PositionPercentYEnabled": true,
                        "PrePosition": {
                          "X": 0.45,
                          "Y": 0.55
                        },
                        "PreSize": {
                          "X": 0.7857,
                          "Y": 0.7442
                        },
                        "LeftMargin": 16.0,
                        "RightMargin": 44.0,
                        "TopMargin": 3.35,
                        "BottomMargin": 7.65,
                        "Tag": 86,
                        "ActionTag": -134985091,
                        "Size": {
                          "X": 220.0,
                          "Y": 32.0
                        },
                        "Name": "lbText",
                        "ctype": "TextObjectData"
                      },
                      {
                        "FileData": {
                          "Type": "Normal",
                          "Path": "Shop/res/BLACKMARKET/Arrow.png",
                          "Plist": ""
                        },
                        "BlendFunc": {
                          "Src": 1,
                          "Dst": 771
                        },
                        "AnchorPoint": {
                          "ScaleX": 0.5,
                          "ScaleY": 0.5
                        },
                        "Position": {
                          "X": 250.0,
                          "Y": 20.0
                        },
                        "Scale": {
                          "ScaleX": 1.5,
                          "ScaleY": 1.5
                        },
                        "CColor": {},
                        "IconVisible": false,
                        "PrePosition": {
                          "X": 0.8929,
                          "Y": 0.4651
                        },
                        "PreSize": {
                          "X": 0.0571,
                          "Y": 0.2093
                        },
                        "HorizontalEdge": "RightEdge",
                        "LeftMargin": 242.0,
                        "RightMargin": 22.0,
                        "TopMargin": 18.5,
                        "BottomMargin": 15.5,
                        "Tag": 104,
                        "ActionTag": 2073907567,
                        "Size": {
                          "X": 16.0,
                          "Y": 9.0
                        },
                        "Name": "imgArrow",
                        "ctype": "SpriteObjectData"
                      }
                    ],
                    "ActionTag": -1420748091,
                    "Size": {
                      "X": 280.0,
                      "Y": 43.0
                    },
                    "Name": "box_sort",
                    "ctype": "ButtonObjectData"
                  },
                  {
                    "FileData": {
                      "Type": "Normal",
                      "Path": "Shop/res/BLACKMARKET/img_box_search.png",
                      "Plist": ""
                    },
                    "Scale9OriginX": 47,
                    "Scale9OriginY": 14,
                    "Scale9Width": 156,
                    "Scale9Height": 29,
                    "StretchWidthEnable": true,
                    "AnchorPoint": {
                      "ScaleX": 0.5,
                      "ScaleY": 0.5
                    },
                    "Position": {
                      "X": 129.886,
                      "Y": 36.0
                    },
                    "Scale": {
                      "ScaleX": 1.0,
                      "ScaleY": 1.0
                    },
                    "CColor": {},
                    "IconVisible": false,
                    "PositionPercentYEnabled": true,
                    "PrePosition": {
                      "X": 0.1286,
                      "Y": 0.6
                    },
                    "PreSize": {
                      "X": 0.2475,
                      "Y": 0.7167
                    },
                    "HorizontalEdge": "LeftEdge",
                    "LeftMargin": 4.886,
                    "RightMargin": 755.114,
                    "TopMargin": 2.5,
                    "BottomMargin": 14.5,
                    "Tag": 111,
                    "Children": [
                      {
                        "FontSize": 28,
                        "IsCustomSize": true,
                        "LabelText": "",
                        "PlaceHolderText": "Search..",
                        "MaxLengthEnable": true,
                        "MaxLengthText": 50,
                        "TouchEnable": true,
                        "AnchorPoint": {
                          "ScaleX": 0.5,
                          "ScaleY": 0.5
                        },
                        "Position": {
                          "X": 125.0,
                          "Y": 20.0
                        },
                        "Scale": {
                          "ScaleX": 1.0,
                          "ScaleY": 1.0
                        },
                        "RotationSkewX": 5.0001,
                        "CColor": {
                          "R": 55,
                          "G": 195,
                          "B": 209
                        },
                        "IconVisible": false,
                        "PrePosition": {
                          "X": 0.5,
                          "Y": 0.4651
                        },
                        "PreSize": {
                          "X": 0.88,
                          "Y": 0.7442
                        },
                        "HorizontalEdge": "LeftEdge",
                        "LeftMargin": 15.0,
                        "RightMargin": 15.0,
                        "TopMargin": 7.0,
                        "BottomMargin": 4.0,
                        "Tag": 175,
                        "ActionTag": -1313088207,
                        "Size": {
                          "X": 220.0,
                          "Y": 32.0
                        },
                        "Name": "tfSearch",
                        "ctype": "TextFieldObjectData"
                      },
                      {
                        "FileData": {
                          "Type": "Normal",
                          "Path": "Shop/res/BLACKMARKET/icon_search_box.png",
                          "Plist": ""
                        },
                        "BlendFunc": {
                          "Src": 1,
                          "Dst": 771
                        },
                        "AnchorPoint": {
                          "ScaleX": 0.5,
                          "ScaleY": 0.5
                        },
                        "Position": {
                          "X": 220.0,
                          "Y": 19.1899
                        },
                        "Scale": {
                          "ScaleX": 1.0,
                          "ScaleY": 1.0
                        },
                        "CColor": {},
                        "IconVisible": false,
                        "PrePosition": {
                          "X": 0.88,
                          "Y": 0.4463
                        },
                        "PreSize": {
                          "X": 0.096,
                          "Y": 0.6512
                        },
                        "HorizontalEdge": "RightEdge",
                        "LeftMargin": 208.0,
                        "RightMargin": 18.0,
                        "TopMargin": 9.8101,
                        "BottomMargin": 5.1899,
                        "Tag": 110,
                        "ActionTag": 1268551311,
                        "Size": {
                          "X": 24.0,
                          "Y": 28.0
                        },
                        "Name": "img_search",
                        "ctype": "SpriteObjectData"
                      }
                    ],
                    "ActionTag": 1931158450,
                    "Size": {
                      "X": 250.0,
                      "Y": 43.0
                    },
                    "Name": "boxSearch",
                    "ctype": "ImageViewObjectData"
                  }
                ],
                "ActionTag": 1249595350,
                "Size": {
                  "X": 1010.0,
                  "Y": 60.0
                },
                "Name": "ndTop",
                "ctype": "PanelObjectData"
              }
            ],
            "ActionTag": 1768891826,
            "Size": {
              "X": 1010.0176,
              "Y": 530.0
            },
            "Name": "bg",
            "ctype": "PanelObjectData"
          }
        ],
        "Size": {
          "X": 1136.0,
          "Y": 640.0
        },
        "Name": "Layer",
        "ctype": "LayerObjectData"
      },
      "UsedResources": [
        "../../Achievement/res/Achievement_new.plist",
        "../../Achievement/res/Achievement_new.png",
        "../../Default/Button_Disable.png",
        "../../Font/facebook.TTF",
        "../res/BLACKMARKET/Arrow.png",
        "../res/BLACKMARKET/Blue_Lines.png",
        "../res/BLACKMARKET/icon_search_box.png",
        "../res/BLACKMARKET/img_box_search.png",
        "../res/BLACKMARKET/Search_Pricedescending_box_02.png"
      ],
      "ctype": "GameFileData"
    }
  },
  "Type": "Layer"
}