{
  "ID": "48b8bdf5-e769-4da0-8638-23c4989dabc8",
  "Version": "2.3.4",
  "Name": "TutorialProcessPopup",
  "Content": {
    "Content": {
      "Animation": {
        "Duration": 0,
        "Speed": 1.0,
        "Timelines": [],
        "ctype": "TimelineActionData"
      },
      "AnimationList": [],
      "ObjectData": {
        "Tag": 83,
        "Children": [
          {
            "FileData": {
              "Type": "PlistSubImage",
              "Path": "workshop_Board_Info.png",
              "Plist": "Workshop/res/Workshop.plist"
            },
            "Scale9Enable": true,
            "Scale9OriginX": 40,
            "Scale9OriginY": 40,
            "Scale9Width": 484,
            "Scale9Height": 434,
            "AnchorPoint": {
              "ScaleX": 0.5,
              "ScaleY": 0.5
            },
            "Position": {
              "X": 0.0,
              "Y": 0.0
            },
            "Scale": {
              "ScaleX": 1.0,
              "ScaleY": 1.0
            },
            "CColor": {},
            "IconVisible": false,
            "PrePosition": {
              "X": 0.0,
              "Y": 0.0
            },
            "PreSize": {
              "X": 0.0,
              "Y": 0.0
            },
            "LeftMargin": -200.0,
            "RightMargin": -200.0,
            "TopMargin": -100.0,
            "BottomMargin": -100.0,
            "Tag": 84,
            "ActionTag": 1969685859,
            "Size": {
              "X": 400.0,
              "Y": 200.0
            },
            "Name": "bg",
            "ctype": "ImageViewObjectData"
          }
        ],
        "Size": {
          "X": 0.0,
          "Y": 0.0
        },
        "Name": "Node",
        "ctype": "SingleNodeObjectData"
      },
      "UsedResources": [
        "../Workshop/res/Workshop.plist",
        "../Workshop/res/Workshop.png"
      ],
      "ctype": "GameFileData"
    }
  },
  "Type": "Node"
}